Metadata-Version: 2.1
Name: neuroc
Version: 0.3.0
Summary: NeuroC: a collection of tools for morphology cloning applications
Author: Blue Brain Project, EPFL
License: Apache-2.0
Project-URL: Homepage, https://github.com/BlueBrain/neuroc
Project-URL: Repository, https://github.com/BlueBrain/neuroc.git
Project-URL: Documentation, https://github.com/BlueBrain/neuroc
Project-URL: Tracker, https://github.com/BlueBrain/neuroc/issues
Classifier: Development Status :: 2 - Pre-Alpha
Classifier: Intended Audience :: Education
Classifier: Intended Audience :: Science/Research
Classifier: Programming Language :: Python
Classifier: Programming Language :: Python :: 3
Classifier: Programming Language :: Python :: 3.9
Classifier: Programming Language :: Python :: 3.10
Classifier: Topic :: Scientific/Engineering :: Bio-Informatics
Requires-Python: >=3.9
License-File: LICENSE.txt
Requires-Dist: attrs>=19.1.0
Requires-Dist: numpy>=1.15.1
Requires-Dist: tqdm>=4.23.4
Requires-Dist: click>=6.7
Requires-Dist: pandas>=1.0.3
Requires-Dist: morphio<4.0,>=3.0
Requires-Dist: morph-tool<3.0,>=2.9.0
Requires-Dist: neurom<4.0,>=3.0
Requires-Dist: scikit-learn<1.5,>=0.21.3
Provides-Extra: plotly
Requires-Dist: neurom[plotly]<4.0,>=3.0; extra == "plotly"
Requires-Dist: dash>=1.1.1; extra == "plotly"
Requires-Dist: dash-html-components>=1.0.0; extra == "plotly"
Requires-Dist: dash-core-components>=1.1.1; extra == "plotly"
Requires-Dist: dash-table>=4.1.0; extra == "plotly"
